<?xml version="1.0" encoding="UTF-8" standalone="yes"?><profile>
	<steamID64>76561198047641872</steamID64>
	<steamID><![CDATA[Folfsky101]]></steamID>
	<onlineState>offline</onlineState>
	<stateMessage><![CDATA[Last Online: ]]></stateMessage>
	<privacyState>friendsonly</privacyState>
	<visibilityState>1</visibilityState>
	<avatarIcon><![CDATA[http://media.steampowered.com/steamcommunity/public/images/avatars/11/110a544db2ffe3512d89a1f16aae07b05d14fc98.jpg]]></avatarIcon>
	<avatarMedium><![CDATA[http://media.steampowered.com/steamcommunity/public/images/avatars/11/110a544db2ffe3512d89a1f16aae07b05d14fc98_medium.jpg]]></avatarMedium>
	<avatarFull><![CDATA[http://media.steampowered.com/steamcommunity/public/images/avatars/11/110a544db2ffe3512d89a1f16aae07b05d14fc98_full.jpg]]></avatarFull>
	<vacBanned>0</vacBanned>
	<tradeBanState>None</tradeBanState>
	<isLimitedAccount>0</isLimitedAccount>
</profile>